contentful_rich_text_to_markdown_converter/__init__.py
contentful_rich_text_to_markdown_converter/adapter.bundle.js
contentful_rich_text_to_markdown_converter/wrapper.py
contentful_rich_text_to_markdown_converter-1.2.dist-info/METADATA
contentful_rich_text_to_markdown_converter-1.2.dist-info/WHEEL
contentful_rich_text_to_markdown_converter-1.2.dist-info/entry_points.txt
contentful_rich_text_to_markdown_converter-1.2.dist-info/top_level.txt
contentful_rich_text_to_markdown_converter-1.2.dist-info/RECORD
